Metadata-Version: 2.1
Name: commonroad-geometric
Version: 0.1.2
Summary: Contains basic functionality for facilitating research on graph neural networks for autonomous driving and provides an interface between CommonRoad and Pytorch Geometric.
Home-page: https://gitlab.lrz.de/cps/commonroad-geometric
Requires-Python: ==3.10.*
License-File: LICENSE.txt
Requires-Dist: aiohttp >=3.8.1
Requires-Dist: bayesian-optimization ==1.3.1
Requires-Dist: class-resolver ==0.3.9
Requires-Dist: commonroad-io ==2022.1
Requires-Dist: commonroad-drivability-checker ==2022.1.1
Requires-Dist: dill ==0.3.6
Requires-Dist: eclipse-sumo ==1.16.0
Requires-Dist: ffmpeg ==1.4
Requires-Dist: geopy ==2.2.0
Requires-Dist: glooey ==0.3.6
Requires-Dist: gymnasium ==0.28.1
Requires-Dist: humanize ==4.1.0
Requires-Dist: hydra-core ==1.2.0
Requires-Dist: iso3166 ==1.0.1
Requires-Dist: libsumo ==1.16.0
Requires-Dist: lxml >=4.3.4
Requires-Dist: matplotlib >=3.3.3
Requires-Dist: networkx ==2.5.1
Requires-Dist: numpy ==1.24.*
Requires-Dist: opendrive2lanelet ==1.1.0
Requires-Dist: optuna ==2.10.0
Requires-Dist: ordered-set ==4.0.2
Requires-Dist: Pillow ==9.4.*
Requires-Dist: pandas ==1.4.1
Requires-Dist: pyglet ==1.5.23
Requires-Dist: python-dotenv ==0.20.0
Requires-Dist: python-statemachine ==0.8.0
Requires-Dist: pytest-cov ==4.1.0
Requires-Dist: rdflib ==6.1.1
Requires-Dist: scikit-learn ==1.2.1
Requires-Dist: scipy ==1.10.1
Requires-Dist: shapely ==1.8.0
Requires-Dist: stable-baselines3 ==2.0.0
Requires-Dist: tensorboard ==2.12.*
Requires-Dist: tqdm >=4.62.3
Requires-Dist: traci ==1.16.0
Requires-Dist: typing-extensions ==4.3.0
Requires-Dist: utm >=0.5.0
Requires-Dist: wandb ==0.12.*
Provides-Extra: tests
Requires-Dist: mypy ; extra == 'tests'
Requires-Dist: pytes ; extra == 'tests'
